mindmeld/__init__.py
mindmeld/_util.py
mindmeld/_version.py
mindmeld/app.py
mindmeld/app_manager.py
mindmeld/augmentation.py
mindmeld/auto_annotator.py
mindmeld/cli.py
mindmeld/constants.py
mindmeld/core.py
mindmeld/exceptions.py
mindmeld/gazetteer.py
mindmeld/markup.py
mindmeld/path.py
mindmeld/query_cache.py
mindmeld/query_factory.py
mindmeld/resource_loader.py
mindmeld/ser.py
mindmeld/server.py
mindmeld/system_entity_recognizer.py
mindmeld/test.py
mindmeld/active_learning/__init__.py
mindmeld/active_learning/alp.py
mindmeld/active_learning/classifiers.py
mindmeld/active_learning/data_loading.py
mindmeld/active_learning/heuristics.py
mindmeld/active_learning/plot_manager.py
mindmeld/active_learning/results_manager.py
mindmeld/bot/__init__.py
mindmeld/bot/webex_bot_server.py
mindmeld/components/__init__.py
mindmeld/components/_config.py
mindmeld/components/_elasticsearch_helpers.py
mindmeld/components/_util.py
mindmeld/components/classifier.py
mindmeld/components/client.py
mindmeld/components/custom_action.py
mindmeld/components/dialogue.py
mindmeld/components/domain_classifier.py
mindmeld/components/entity_recognizer.py
mindmeld/components/entity_resolver.py
mindmeld/components/intent_classifier.py
mindmeld/components/nlp.py
mindmeld/components/parser.py
mindmeld/components/question_answerer.py
mindmeld/components/request.py
mindmeld/components/role_classifier.py
mindmeld/components/schemas.py
mindmeld/components/translators.py
mindmeld/converter/README.md
mindmeld/converter/__init__.py
mindmeld/converter/code_generator.py
mindmeld/converter/converter.py
mindmeld/converter/dialogflow.py
mindmeld/converter/greetings.txt
mindmeld/converter/rasa.py
mindmeld/converter/rasa_custom_features.txt
mindmeld/converter/template_main.txt
mindmeld/converter/unrelated.txt
mindmeld/kwik_e_mart/__init__.py
mindmeld/kwik_e_mart/__main__.py
mindmeld/kwik_e_mart/app_async.py
mindmeld/kwik_e_mart/config.py
mindmeld/kwik_e_mart/custom_features.py
mindmeld/kwik_e_mart/requirements.txt
mindmeld-4.6.2.dist-info/AUTHORS
mindmeld-4.6.2.dist-info/LICENSE
mindmeld-4.6.2.dist-info/METADATA
mindmeld-4.6.2.dist-info/NOTICE
mindmeld-4.6.2.dist-info/WHEEL
mindmeld-4.6.2.dist-info/entry_points.txt
mindmeld-4.6.2.dist-info/top_level.txt
mindmeld-4.6.2.dist-info/RECORD
