Metadata-Version: 2.1
Name: mindmeld
Version: 4.6.2
Summary: A Conversational AI platform.
Home-page: https://github.com/cisco/mindmeld
Author: Cisco Systems, Inc.
Author-email: contact@mindmeld.com
Keywords: mindmeld,nlp,ai,conversational
Classifier: Development Status :: 5 - Production/Stable
Classifier: Intended Audience :: Developers
Classifier: Natural Language :: English
Classifier: Programming Language :: Python :: 3
Classifier: Programming Language :: Python :: 3.6
Classifier: Programming Language :: Python :: 3.7
Classifier: Topic :: Scientific/Engineering :: Artificial Intelligence
Classifier: Topic :: Software Development :: Libraries :: Application Frameworks
Classifier: License :: OSI Approved :: Apache Software License
License-File: LICENSE
License-File: NOTICE
License-File: AUTHORS
Requires-Dist: aiohttp (>=3.6.2)
Requires-Dist: attrs (>=18.2)
Requires-Dist: Click (~=7.1)
Requires-Dist: click-log (==0.1.8)
Requires-Dist: distro (~=1.3)
Requires-Dist: elasticsearch (<7.14,>=5.0)
Requires-Dist: Flask (<2,>=1.1.3)
Requires-Dist: Flask-Cors (~=3.0)
Requires-Dist: future (~=0.17)
Requires-Dist: pycountry
Requires-Dist: nltk (~=3.2)
Requires-Dist: numpy (~=1.15)
Requires-Dist: pip (>=9.0.1)
Requires-Dist: py (~=1.4)
Requires-Dist: python-dateutil (~=2.6)
Requires-Dist: pytz
Requires-Dist: scipy (<2.0,>=0.13.3)
Requires-Dist: requests (<3.0,>=2.20.1)
Requires-Dist: tqdm (~=4.15)
Requires-Dist: sklearn-crfsuite (<1.0,>=0.3.6)
Requires-Dist: immutables (~=0.9)
Requires-Dist: pyyaml (>=5.1.1)
Requires-Dist: spacy (!=2.3.6,~=2.3)
Requires-Dist: mypy (>=0.782)
Requires-Dist: marshmallow (~=3.7.1)
Requires-Dist: markupsafe (==2.0.1)
Requires-Dist: pytorch-crf (~=0.7.2)
Requires-Dist: scikit-learn (<0.20,>=0.18.1) ; python_version < "3.7"
Requires-Dist: python-crfsuite (~=0.9) ; python_version < "3.7"
Requires-Dist: torch (~=1.10.0) ; python_version >= "3.6"
Requires-Dist: dataclasses (<0.8,>=0.7) ; python_version >= "3.6" and python_version < "3.7"
Requires-Dist: scikit-learn (<0.20,>=0.19.2) ; python_version >= "3.7"
Requires-Dist: python-crfsuite (<1.0,>=0.9.6) ; python_version >= "3.7"
Provides-Extra: active_learning
Requires-Dist: matplotlib (~=3.3.1) ; extra == 'active_learning'
Provides-Extra: augment
Requires-Dist: sentencepiece (==0.1.91) ; extra == 'augment'
Requires-Dist: torch (~=1.10.0) ; (python_version >= "3.6") and extra == 'augment'
Requires-Dist: transformers (~=4.15.0) ; (python_version >= "3.6") and extra == 'augment'
Provides-Extra: bert
Requires-Dist: elasticsearch (<7.14,>=7.0) ; extra == 'bert'
Requires-Dist: torch (~=1.10.0) ; (python_version >= "3.6") and extra == 'bert'
Requires-Dist: transformers (~=4.15.0) ; (python_version >= "3.6") and extra == 'bert'
Requires-Dist: sentence-transformers (~=0.3) ; (python_version >= "3.6") and extra == 'bert'
Provides-Extra: bot
Requires-Dist: ciscosparkapi ; extra == 'bot'
Requires-Dist: twilio ; extra == 'bot'
Provides-Extra: dvc
Requires-Dist: dvc (>=1.8.1) ; extra == 'dvc'
Requires-Dist: pygit2 (<1.7,>=1.5.0) ; (python_version < "3.7") and extra == 'dvc'
Provides-Extra: elasticsearch
Requires-Dist: elasticsearch (<7.14,>=5.0) ; extra == 'elasticsearch'
Provides-Extra: examples
Requires-Dist: connexion (>=2.7.0) ; (python_version >= "3.6") and extra == 'examples'
Provides-Extra: language_annotator
Requires-Dist: google-cloud-translate (>=3.0.1) ; extra == 'language_annotator'
Provides-Extra: tensorflow
Requires-Dist: tensorflow (~=1.2) ; (python_version < "3.7") and extra == 'tensorflow'
Requires-Dist: tensorflow (<2.0,>=1.13.1) ; (python_version >= "3.7") and extra == 'tensorflow'
Provides-Extra: transformers
Requires-Dist: transformers (~=4.15.0) ; (python_version >= "3.6") and extra == 'transformers'
